guildwatcher.py
guildwatcher-2.0.0.dist-info/LICENSE
guildwatcher-2.0.0.dist-info/METADATA
guildwatcher-2.0.0.dist-info/WHEEL
guildwatcher-2.0.0.dist-info/entry_points.txt
guildwatcher-2.0.0.dist-info/top_level.txt
guildwatcher-2.0.0.dist-info/RECORD
