Metadata-Version: 2.1
Name: guildwatcher
Version: 2.0.0
Summary: A discord webhook to track Tibia guild changes.
Home-page: https://github.com/Galarzaa90/GuildWatcher
Author: Allan Galarza
Author-email: allan.galarza@gmail.com
License: MIT
Project-URL: Coverage: Codecov, https://codecov.io/gh/Galarzaa90/GuildWatcher/
Platform: UNKNOWN
Classifier: Development Status :: 5 - Production/Stable
Classifier: Environment :: Console
Classifier: License :: OSI Approved :: MIT License
Classifier: Natural Language :: English
Classifier: Operating System :: OS Independent
Classifier: Programming Language :: Python :: 3 :: Only
Classifier: Programming Language :: Python :: 3.6
Classifier: Programming Language :: Python :: 3.7
Classifier: Programming Language :: Python :: 3.8
Classifier: Programming Language :: Python :: 3.9
Classifier: Topic :: Communications :: Chat
Classifier: Topic :: Games/Entertainment
Classifier: Topic :: Games/Entertainment :: Role-Playing
Requires-Python: >=3.6
Requires-Dist: requests
Requires-Dist: tibia.py
Requires-Dist: PyYAML
